histore/__init__.py
histore/config.py
histore/key.py
histore/util.py
histore/version.py
histore/archive/__init__.py
histore/archive/base.py
histore/archive/merge.py
histore/archive/reader.py
histore/archive/row.py
histore/archive/schema.py
histore/archive/snapshot.py
histore/archive/timestamp.py
histore/archive/value.py
histore/archive/writer.py
histore/archive/manager/__init__.py
histore/archive/manager/base.py
histore/archive/manager/descriptor.py
histore/archive/manager/fs.py
histore/archive/manager/mem.py
histore/archive/manager/persist.py
histore/archive/manager/db/__init__.py
histore/archive/manager/db/base.py
histore/archive/manager/db/database.py
histore/archive/manager/db/model.py
histore/archive/provenance/__init__.py
histore/archive/provenance/archive.py
histore/archive/provenance/base.py
histore/archive/provenance/column.py
histore/archive/provenance/describe.py
histore/archive/provenance/row.py
histore/archive/provenance/value.py
histore/archive/serialize/__init__.py
histore/archive/serialize/base.py
histore/archive/serialize/compact.py
histore/archive/serialize/default.py
histore/archive/store/__init__.py
histore/archive/store/base.py
histore/archive/store/fs/__init__.py
histore/archive/store/fs/base.py
histore/archive/store/fs/reader.py
histore/archive/store/fs/writer.py
histore/archive/store/mem/__init__.py
histore/archive/store/mem/base.py
histore/archive/store/mem/reader.py
histore/archive/store/mem/writer.py
histore/cli/__init__.py
histore/cli/archive.py
histore/cli/base.py
histore/cli/snapshot.py
histore/document/__init__.py
histore/document/base.py
histore/document/df.py
histore/document/external.py
histore/document/mem.py
histore/document/operator.py
histore/document/reader.py
histore/document/row.py
histore/document/schema.py
histore/document/sort.py
histore/document/csv/__init__.py
histore/document/csv/base.py
histore/document/csv/reader.py
histore/document/csv/writer.py
histore/document/json/__init__.py
histore/document/json/base.py
histore-0.4.1.dist-info/LICENSE
histore-0.4.1.dist-info/METADATA
histore-0.4.1.dist-info/WHEEL
histore-0.4.1.dist-info/entry_points.txt
histore-0.4.1.dist-info/top_level.txt
histore-0.4.1.dist-info/RECORD
