Metadata-Version: 2.1
Name: histore
Version: 0.4.1
Summary: Library for maintaining evolving tabular data sets
Home-page: https://github.com/heikomuller/histore
Author: Heiko Mueller
Author-email: heiko.muller@gmail.com
License: New BSD
Keywords: data versioning
Platform: UNKNOWN
Classifier: License :: OSI Approved :: BSD License
Classifier: Operating System :: OS Independent
Classifier: Programming Language :: Python :: 3
Classifier: Programming Language :: Python :: 3.7
Classifier: Programming Language :: Python :: 3.8
Classifier: Programming Language :: Python :: 3.9
Classifier: Programming Language :: Python
Requires-Dist: future
Requires-Dist: appdirs (>=1.4.4)
Requires-Dist: pandas (>=1.0.0)
Requires-Dist: jsonschema (>=3.2.0)
Requires-Dist: python-dateutil
Requires-Dist: pyyaml
Requires-Dist: psutil
Requires-Dist: SQLAlchemy (>=1.3.18)
Requires-Dist: Click (>=7.0)
Provides-Extra: dev
Requires-Dist: flake8 ; extra == 'dev'
Requires-Dist: python-language-server ; extra == 'dev'
Requires-Dist: coverage (>=4.0) ; extra == 'dev'
Requires-Dist: pytest ; extra == 'dev'
Requires-Dist: pytest-cov ; extra == 'dev'
Provides-Extra: docs
Requires-Dist: Sphinx ; extra == 'docs'
Requires-Dist: sphinx-rtd-theme ; extra == 'docs'
Requires-Dist: sphinxcontrib-apidoc ; extra == 'docs'
Provides-Extra: tests
Requires-Dist: coverage (>=4.0) ; extra == 'tests'
Requires-Dist: pytest ; extra == 'tests'
Requires-Dist: pytest-cov ; extra == 'tests'
